README
setup.py
ptrcreate.egg-info/PKG-INFO
ptrcreate.egg-info/SOURCES.txt
ptrcreate.egg-info/dependency_links.txt
ptrcreate.egg-info/entry_points.txt
ptrcreate.egg-info/top_level.txt
raxptr/__init__.py
raxptr/info.py
raxptr/ptrcreate.py